nuri/__init__.py
nuri/config.py
nuri/extensions.py
nuri/jinja_utils.py
nuri/models/__init__.py
nuri/models/access.py
nuri/models/asset.py
nuri/models/base.py
nuri/models/collection.py
nuri/models/content.py
nuri/models/field.py
nuri/models/field_type.py
nuri/models/request_method.py
nuri/models/role.py
nuri/models/user.py
nuri/models/webhook.py
nuri/models/webhook_item.py
nuri/models/webhook_type.py
nuri/services/__init__.py
nuri/services/paginate.py
nuri/services/webhook.py
nuri/utils/__init__.py
nuri/utils/message.py
nuri/views/__init__.py
nuri/views/access.py
nuri/views/asset.py
nuri/views/collection.py
nuri/views/content.py
nuri/views/field.py
nuri/views/home.py
nuri/views/user.py
nuri/views/webhook.py
nuri/views/api/__init__.py
nuri/views/api/utils.py
nuri/views/api/view.py
nuri/views/auth/__init__.py
nuri/views/auth/auth.py
nuri/views/auth/utils.py
nuri_cms-0.2.0.dist-info/LICENSE
nuri_cms-0.2.0.dist-info/METADATA
nuri_cms-0.2.0.dist-info/WHEEL
nuri_cms-0.2.0.dist-info/top_level.txt
nuri_cms-0.2.0.dist-info/RECORD
